client/freeFile.py
client/initConfig.py
client/API/ApplyApi.py
client/API/CreateArchive.py
client/API/PullArchive.py
client/API/PushArchive.py
freeFile-0.2.0.data/scripts/ff
freeFile-0.2.0.dist-info/METADATA
freeFile-0.2.0.dist-info/RECORD
freeFile-0.2.0.dist-info/WHEEL
freeFile-0.2.0.dist-info/top_level.txt
